SentimentModel/SentimentModel.py
SentimentModel/VERSION
SentimentModel/__init__.py
SentimentModel/config.yml
SentimentModel/model.py
SentimentModel/pipeline.py
SentimentModel/prediction.py
SentimentModel/training.py
SentimentModel/word_embeddings.py
SentimentModel/Config/__init__.py
SentimentModel/Config/core.py
SentimentModel/Config/logging_config.py
SentimentModel/Processing/__init__.py
SentimentModel/Processing/data_management.py
SentimentModel/Processing/preprocessing.py
SentimentModel-1.0.1.dist-info/LICENSE
SentimentModel-1.0.1.dist-info/METADATA
SentimentModel-1.0.1.dist-info/WHEEL
SentimentModel-1.0.1.dist-info/top_level.txt
SentimentModel-1.0.1.dist-info/RECORD
