Metadata-Version: 2.1
Name: SentimentModel
Version: 1.0.1
Summary: Sentiment analysis model
Home-page: https://github.com/HassanRady/SentimentModel
Author: Hassan Rady
Author-email: hassan.khaled.rady@gmail.com
License: MIT license
Keywords: Sentiment
Classifier: Development Status :: 2 - Pre-Alpha
Classifier: Intended Audience :: Developers
Classifier: License :: OSI Approved :: MIT License
Classifier: Natural Language :: English
Classifier: Programming Language :: Python :: 3
Classifier: Programming Language :: Python :: 3.6
Classifier: Programming Language :: Python :: 3.7
Classifier: Programming Language :: Python :: 3.8
Requires-Python: >=3.9.0
License-File: LICENSE
Requires-Dist: joblib
Requires-Dist: pandas
Requires-Dist: pydantic
Requires-Dist: scikit-learn
Requires-Dist: strictyaml
Requires-Dist: tensorflow
